[
  {
    "package": {
      "name": "flows",
      "version": {
        "workspace": true
      },
      "authors": {
        "workspace": true
      },
      "edition": {
        "workspace": true
      },
      "description": "Building blocks for flow-based programming (FBP).",
      "readme": {
        "workspace": true
      },
      "homepage": {
        "workspace": true
      },
      "repository": {
        "workspace": true
      },
      "license": {
        "workspace": true
      },
      "keywords": {
        "workspace": true
      },
      "categories": {
        "workspace": true
      },
      "publish": {
        "workspace": true
      },
      "metadata": {
        "readme": {
          "title": "Flows.rs"
        }
      }
    },
    "features": {
      "default": [
        "core",
        "std"
      ],
      "core": [
        "derive",
        "io",
        "math",
        "text"
      ],
      "all": [
        "arrow",
        "audio",
        "datafusion",
        "derive",
        "dns",
        "hash",
        "http",
        "image",
        "io",
        "json",
        "math",
        "mdns",
        "pubsub",
        "rand",
        "text",
        "video"
      ],
      "std": [
        "async-flow/std",
        "flows-arrow?/std",
        "flows-audio?/std",
        "flows-datafusion?/std",
        "flows-derive?/std",
        "flows-dns?/std",
        "flows-hash?/std",
        "flows-http?/std",
        "flows-image?/std",
        "flows-io?/std",
        "flows-json?/std",
        "flows-math?/std",
        "flows-mdns?/std",
        "flows-pubsub?/std",
        "flows-rand?/std",
        "flows-text?/std",
        "flows-video?/std"
      ],
      "unstable": [],
      "arrow": [
        "dep:flows-arrow"
      ],
      "audio": [
        "dep:flows-audio"
      ],
      "datafusion": [
        "dep:flows-datafusion"
      ],
      "derive": [
        "dep:flows-derive"
      ],
      "dns": [
        "dep:flows-dns"
      ],
      "hash": [
        "dep:flows-hash"
      ],
      "http": [
        "dep:flows-http"
      ],
      "image": [
        "dep:flows-image"
      ],
      "io": [
        "dep:flows-io"
      ],
      "json": [
        "dep:flows-json"
      ],
      "math": [
        "dep:flows-math"
      ],
      "mdns": [
        "dep:flows-mdns"
      ],
      "pubsub": [
        "dep:flows-pubsub"
      ],
      "rand": [
        "dep:flows-rand"
      ],
      "text": [
        "dep:flows-text"
      ],
      "video": [
        "dep:flows-video"
      ],
      "serde": []
    },
    "dependencies": {
      "async-flow": {
        "workspace": true
      },
      "tokio": {
        "workspace": true,
        "features": [
          "full"
        ]
      },
      "valuand": {
        "version": "0.0.1",
        "default-features": false,
        "features": [
          "alloc"
        ]
      },
      "flows-arrow": {
        "workspace": true,
        "features": [],
        "optional": true
      },
      "flows-audio": {
        "workspace": true,
        "features": [],
        "optional": true
      },
      "flows-datafusion": {
        "workspace": true,
        "features": [],
        "optional": true
      },
      "flows-derive": {
        "workspace": true,
        "features": [],
        "optional": true
      },
      "flows-dns": {
        "workspace": true,
        "features": [],
        "optional": true
      },
      "flows-hash": {
        "workspace": true,
        "features": [],
        "optional": true
      },
      "flows-http": {
        "workspace": true,
        "features": [],
        "optional": true
      },
      "flows-image": {
        "workspace": true,
        "features": [],
        "optional": true
      },
      "flows-io": {
        "workspace": true,
        "features": [],
        "optional": true
      },
      "flows-json": {
        "workspace": true,
        "features": [],
        "optional": true
      },
      "flows-math": {
        "workspace": true,
        "features": [],
        "optional": true
      },
      "flows-mdns": {
        "workspace": true,
        "features": [],
        "optional": true
      },
      "flows-pubsub": {
        "workspace": true,
        "features": [],
        "optional": true
      },
      "flows-rand": {
        "workspace": true,
        "features": [],
        "optional": true
      },
      "flows-text": {
        "workspace": true,
        "features": [],
        "optional": true
      },
      "flows-video": {
        "workspace": true,
        "features": [],
        "optional": true
      }
    },
    "dev-dependencies": {
      "tokio": {
        "workspace": true
      }
    }
  },
  {
    "package": {
      "name": "flows-arrow",
      "version": {
        "workspace": true
      },
      "authors": {
        "workspace": true
      },
      "edition": {
        "workspace": true
      },
      "description": "Building blocks for flow-based data processing with Apache Arrow.",
      "readme": true,
      "homepage": {
        "workspace": true
      },
      "repository": {
        "workspace": true
      },
      "license": {
        "workspace": true
      },
      "keywords": {
        "workspace": true
      },
      "categories": {
        "workspace": true
      },
      "publish": {
        "workspace": true
      },
      "metadata": {
        "readme": {
          "title": "Flows.rs: Data Processing with Apache Arrow"
        }
      }
    },
    "features": {
      "default": [
        "all",
        "std"
      ],
      "all": [],
      "std": [
        "async-flow/std"
      ],
      "unstable": []
    },
    "dependencies": {
      "arrow-array": {
        "version": "57.2",
        "default-features": false
      },
      "arrow-select": {
        "version": "57.2",
        "default-features": false
      },
      "async-flow": {
        "workspace": true
      },
      "flows-derive": {
        "workspace": true
      },
      "tokio": {
        "workspace": true
      }
    },
    "target": {
      "cfg(not(target_family = \"wasm\"))": {
        "dependencies": {}
      },
      "cfg(target_family = \"wasm\")": {
        "dependencies": {}
      }
    },
    "dev-dependencies": {
      "arrow-schema": {
        "version": "57.2",
        "default-features": false
      },
      "tokio": {
        "workspace": true
      }
    }
  },
  {
    "package": {
      "name": "flows-audio",
      "version": {
        "workspace": true
      },
      "authors": {
        "workspace": true
      },
      "edition": {
        "workspace": true
      },
      "description": "Building blocks for flow-based audio processing.",
      "readme": true,
      "homepage": {
        "workspace": true
      },
      "repository": {
        "workspace": true
      },
      "license": {
        "workspace": true
      },
      "keywords": {
        "workspace": true
      },
      "categories": {
        "workspace": true
      },
      "publish": {
        "workspace": true
      },
      "metadata": {
        "readme": {
          "title": "Flows.rs: Audio Processing"
        }
      }
    },
    "features": {
      "default": [
        "all",
        "std"
      ],
      "all": [],
      "std": [
        "async-flow/std"
      ],
      "unstable": []
    },
    "dependencies": {
      "async-flow": {
        "workspace": true
      },
      "flows-derive": {
        "workspace": true
      },
      "symphonia": {
        "version": "0.5",
        "default-features": false
      }
    },
    "target": {
      "cfg(not(target_family = \"wasm\"))": {
        "dependencies": {}
      },
      "cfg(target_family = \"wasm\")": {
        "dependencies": {}
      }
    }
  },
  {
    "package": {
      "name": "flows-datafusion",
      "version": {
        "workspace": true
      },
      "authors": {
        "workspace": true
      },
      "edition": {
        "workspace": true
      },
      "description": "Building blocks for flow-based query processing with Apache DataFusion.",
      "readme": true,
      "homepage": {
        "workspace": true
      },
      "repository": {
        "workspace": true
      },
      "license": {
        "workspace": true
      },
      "keywords": {
        "workspace": true
      },
      "categories": {
        "workspace": true
      },
      "publish": {
        "workspace": true
      },
      "metadata": {
        "readme": {
          "title": "Flows.rs: Query Processing with Apache DataFusion"
        }
      }
    },
    "features": {
      "default": [
        "all",
        "std"
      ],
      "all": [],
      "std": [
        "async-flow/std"
      ],
      "unstable": []
    },
    "dependencies": {
      "arrow-arith": {
        "version": "57.2",
        "default-features": false
      },
      "arrow-array": {
        "version": "57.2",
        "default-features": false
      },
      "arrow-schema": {
        "version": "57.2",
        "default-features": false
      },
      "async-flow": {
        "workspace": true
      },
      "datafusion-common": {
        "version": "52",
        "default-features": false
      },
      "flows-arrow": {
        "workspace": true
      },
      "flows-derive": {
        "workspace": true
      },
      "tokio": {
        "workspace": true
      }
    },
    "target": {
      "cfg(not(target_family = \"wasm\"))": {
        "dependencies": {}
      },
      "cfg(target_family = \"wasm\")": {
        "dependencies": {}
      }
    },
    "dev-dependencies": {
      "tokio": {
        "workspace": true
      }
    }
  },
  {
    "package": {
      "name": "flows-derive",
      "version": {
        "workspace": true
      },
      "authors": {
        "workspace": true
      },
      "edition": {
        "workspace": true
      },
      "description": "Derive macros for flow-based programming (FBP).",
      "readme": true,
      "homepage": {
        "workspace": true
      },
      "repository": {
        "workspace": true
      },
      "license": {
        "workspace": true
      },
      "keywords": {
        "workspace": true
      },
      "categories": {
        "workspace": true
      },
      "publish": {
        "workspace": true
      },
      "metadata": {
        "readme": {
          "title": "Flows.rs: Derive Macros"
        }
      }
    },
    "features": {
      "default": [
        "all",
        "std"
      ],
      "all": [],
      "std": [
        "async-flow/std"
      ],
      "unstable": []
    },
    "dependencies": {
      "async-flow": {
        "workspace": true
      },
      "darling": {
        "version": "0.23",
        "default-features": false
      },
      "quote": "1.0",
      "proc-macro2": "1.0",
      "syn": {
        "version": "2.0",
        "features": [
          "full",
          "extra-traits"
        ]
      },
      "syn-match": "0.3",
      "syn-path": "2.1"
    },
    "target": {
      "cfg(not(target_family = \"wasm\"))": {
        "dependencies": {}
      },
      "cfg(target_family = \"wasm\")": {
        "dependencies": {}
      }
    },
    "lib": {
      "proc-macro": true
    }
  },
  {
    "package": {
      "name": "flows-dns",
      "version": {
        "workspace": true
      },
      "authors": {
        "workspace": true
      },
      "edition": {
        "workspace": true
      },
      "description": "Building blocks for flow-based DNS resolution.",
      "readme": true,
      "homepage": {
        "workspace": true
      },
      "repository": {
        "workspace": true
      },
      "license": {
        "workspace": true
      },
      "keywords": {
        "workspace": true
      },
      "categories": {
        "workspace": true
      },
      "publish": {
        "workspace": true
      },
      "metadata": {
        "readme": {
          "title": "Flows.rs: DNS Resolution"
        }
      }
    },
    "features": {
      "default": [
        "all",
        "std"
      ],
      "all": [],
      "std": [
        "async-flow/std"
      ],
      "unstable": []
    },
    "dependencies": {
      "async-flow": {
        "workspace": true
      },
      "flows-derive": {
        "workspace": true
      },
      "hickory-resolver": {
        "version": "0.25",
        "default-features": false
      }
    },
    "target": {
      "cfg(not(target_family = \"wasm\"))": {
        "dependencies": {}
      },
      "cfg(target_family = \"wasm\")": {
        "dependencies": {}
      }
    }
  },
  {
    "package": {
      "name": "flows-hash",
      "version": {
        "workspace": true
      },
      "authors": {
        "workspace": true
      },
      "edition": {
        "workspace": true
      },
      "description": "Building blocks for flow-based cryptographic hashing.",
      "readme": true,
      "homepage": {
        "workspace": true
      },
      "repository": {
        "workspace": true
      },
      "license": {
        "workspace": true
      },
      "keywords": {
        "workspace": true
      },
      "categories": {
        "workspace": true
      },
      "publish": {
        "workspace": true
      },
      "metadata": {
        "readme": {
          "title": "Flows.rs: Cryptographic Hashing"
        }
      }
    },
    "features": {
      "default": [
        "all",
        "std"
      ],
      "all": [],
      "std": [
        "async-flow/std"
      ],
      "unstable": [],
      "blake3": [],
      "md5": [
        "dep:md-5"
      ],
      "sha1": [
        "dep:sha1"
      ],
      "sha2": [
        "dep:sha2"
      ]
    },
    "dependencies": {
      "async-flow": {
        "workspace": true
      },
      "flows-derive": {
        "workspace": true
      },
      "md-5": {
        "version": "0.10",
        "default-features": false,
        "optional": true
      },
      "sha1": {
        "version": "0.10",
        "default-features": false,
        "optional": true
      },
      "sha2": {
        "version": "0.10",
        "default-features": false,
        "optional": true
      }
    },
    "target": {
      "cfg(not(target_family = \"wasm\"))": {
        "dependencies": {}
      },
      "cfg(target_family = \"wasm\")": {
        "dependencies": {}
      }
    }
  },
  {
    "package": {
      "name": "flows-http",
      "version": {
        "workspace": true
      },
      "authors": {
        "workspace": true
      },
      "edition": {
        "workspace": true
      },
      "description": "Building blocks for flow-based HTTP requests & responses.",
      "readme": true,
      "homepage": {
        "workspace": true
      },
      "repository": {
        "workspace": true
      },
      "license": {
        "workspace": true
      },
      "keywords": {
        "workspace": true
      },
      "categories": {
        "workspace": true
      },
      "publish": {
        "workspace": true
      },
      "metadata": {
        "readme": {
          "title": "Flows.rs: HTTP Requests & Responses"
        }
      }
    },
    "features": {
      "default": [
        "all",
        "std"
      ],
      "all": [
        "http1",
        "http2"
      ],
      "std": [
        "async-flow/std"
      ],
      "unstable": [],
      "http1": [
        "hyper/http1",
        "hyper-rustls?/http1",
        "hyper-util/http1"
      ],
      "http2": [
        "hyper/http2",
        "hyper-rustls?/http2",
        "hyper-util/http2",
        "tls"
      ],
      "tls": [
        "rustls"
      ],
      "rustls": [
        "dep:hyper-rustls",
        "dep:rustls",
        "dep:rustls-platform-verifier"
      ]
    },
    "dependencies": {
      "async-flow": {
        "workspace": true
      },
      "flows-derive": {
        "workspace": true
      },
      "http": {
        "version": "1.4",
        "default-features": false
      },
      "hyper": {
        "version": "1",
        "default-features": false,
        "features": [
          "client"
        ]
      },
      "hyper-util": {
        "version": "0.1",
        "default-features": false,
        "features": [
          "tokio"
        ]
      },
      "thiserror": {
        "version": "2",
        "default-features": false
      },
      "tokio": {
        "version": "1",
        "default-features": false,
        "features": [
          "net"
        ]
      },
      "hyper-rustls": {
        "version": "0.27",
        "default-features": false,
        "optional": true
      },
      "rustls": {
        "version": "0.23",
        "default-features": false,
        "features": [
          "ring"
        ],
        "optional": true
      },
      "rustls-platform-verifier": {
        "version": "0.5",
        "default-features": false,
        "optional": true
      }
    },
    "target": {
      "cfg(not(target_family = \"wasm\"))": {
        "dependencies": {}
      },
      "cfg(target_family = \"wasm\")": {
        "dependencies": {}
      }
    }
  },
  {
    "package": {
      "name": "flows-image",
      "version": {
        "workspace": true
      },
      "authors": {
        "workspace": true
      },
      "edition": {
        "workspace": true
      },
      "description": "Building blocks for flow-based image processing.",
      "readme": true,
      "homepage": {
        "workspace": true
      },
      "repository": {
        "workspace": true
      },
      "license": {
        "workspace": true
      },
      "keywords": {
        "workspace": true
      },
      "categories": {
        "workspace": true
      },
      "publish": {
        "workspace": true
      },
      "metadata": {
        "readme": {
          "title": "Flows.rs: Image Processing"
        }
      }
    },
    "features": {
      "default": [
        "all",
        "std"
      ],
      "all": [],
      "std": [
        "async-flow/std"
      ],
      "unstable": []
    },
    "dependencies": {
      "async-flow": {
        "workspace": true
      },
      "flows-derive": {
        "workspace": true
      },
      "image": {
        "version": "0.25",
        "default-features": false
      },
      "rgb": {
        "version": "0.8",
        "default-features": false
      }
    },
    "target": {
      "cfg(not(target_family = \"wasm\"))": {
        "dependencies": {}
      },
      "cfg(target_family = \"wasm\")": {
        "dependencies": {}
      }
    }
  },
  {
    "package": {
      "name": "flows-io",
      "version": {
        "workspace": true
      },
      "authors": {
        "workspace": true
      },
      "edition": {
        "workspace": true
      },
      "description": "Building blocks for flow-based I/O readers & writers.",
      "readme": true,
      "homepage": {
        "workspace": true
      },
      "repository": {
        "workspace": true
      },
      "license": {
        "workspace": true
      },
      "keywords": {
        "workspace": true
      },
      "categories": {
        "workspace": true
      },
      "publish": {
        "workspace": true
      },
      "metadata": {
        "readme": {
          "title": "Flows.rs: I/O Readers & Writers"
        }
      }
    },
    "features": {
      "default": [
        "all",
        "std"
      ],
      "all": [],
      "std": [
        "async-flow/std"
      ],
      "unstable": []
    },
    "dependencies": {
      "async-flow": {
        "workspace": true
      },
      "flows-derive": {
        "workspace": true
      }
    },
    "target": {
      "cfg(not(target_family = \"wasm\"))": {
        "dependencies": {}
      },
      "cfg(target_family = \"wasm\")": {
        "dependencies": {}
      }
    }
  },
  {
    "package": {
      "name": "flows-json",
      "version": {
        "workspace": true
      },
      "authors": {
        "workspace": true
      },
      "edition": {
        "workspace": true
      },
      "description": "Building blocks for flow-based JSON encoding & decoding.",
      "readme": true,
      "homepage": {
        "workspace": true
      },
      "repository": {
        "workspace": true
      },
      "license": {
        "workspace": true
      },
      "keywords": {
        "workspace": true
      },
      "categories": {
        "workspace": true
      },
      "publish": {
        "workspace": true
      },
      "metadata": {
        "readme": {
          "title": "Flows.rs: JSON Encoding & Decoding"
        }
      }
    },
    "features": {
      "default": [
        "all",
        "std"
      ],
      "all": [],
      "std": [
        "async-flow/std",
        "serde_json/std"
      ],
      "unstable": []
    },
    "dependencies": {
      "async-flow": {
        "workspace": true,
        "features": [
          "serde"
        ]
      },
      "flows-derive": {
        "workspace": true
      },
      "serde_json": {
        "version": "1",
        "default-features": false,
        "features": [
          "alloc"
        ]
      }
    },
    "target": {
      "cfg(not(target_family = \"wasm\"))": {
        "dependencies": {}
      },
      "cfg(target_family = \"wasm\")": {
        "dependencies": {}
      }
    }
  },
  {
    "package": {
      "name": "flows-math",
      "version": {
        "workspace": true
      },
      "authors": {
        "workspace": true
      },
      "edition": {
        "workspace": true
      },
      "description": "Building blocks for flow-based mathematical operations.",
      "readme": true,
      "homepage": {
        "workspace": true
      },
      "repository": {
        "workspace": true
      },
      "license": {
        "workspace": true
      },
      "keywords": {
        "workspace": true
      },
      "categories": {
        "workspace": true
      },
      "publish": {
        "workspace": true
      },
      "metadata": {
        "readme": {
          "title": "Flows.rs: Mathematical Operations"
        }
      }
    },
    "features": {
      "default": [
        "all",
        "std"
      ],
      "all": [],
      "std": [
        "async-flow/std"
      ],
      "unstable": []
    },
    "dependencies": {
      "async-flow": {
        "workspace": true
      },
      "flows-derive": {
        "workspace": true
      },
      "num-traits": {
        "version": "0.2",
        "default-features": false,
        "optional": true
      },
      "tokio": {
        "workspace": true
      }
    },
    "target": {
      "cfg(not(target_family = \"wasm\"))": {
        "dependencies": {}
      },
      "cfg(target_family = \"wasm\")": {
        "dependencies": {}
      }
    },
    "dev-dependencies": {
      "tokio": {
        "workspace": true
      }
    }
  },
  {
    "package": {
      "name": "flows-mdns",
      "version": {
        "workspace": true
      },
      "authors": {
        "workspace": true
      },
      "edition": {
        "workspace": true
      },
      "description": "Building blocks for flow-based mDNS discovery.",
      "readme": true,
      "homepage": {
        "workspace": true
      },
      "repository": {
        "workspace": true
      },
      "license": {
        "workspace": true
      },
      "keywords": {
        "workspace": true
      },
      "categories": {
        "workspace": true
      },
      "publish": {
        "workspace": true
      },
      "metadata": {
        "readme": {
          "title": "Flows.rs: mDNS Discovery"
        }
      }
    },
    "features": {
      "default": [
        "all",
        "std"
      ],
      "all": [],
      "std": [
        "async-flow/std"
      ],
      "unstable": []
    },
    "dependencies": {
      "async-flow": {
        "workspace": true
      },
      "flows-derive": {
        "workspace": true
      }
    },
    "target": {
      "cfg(not(target_family = \"wasm\"))": {
        "dependencies": {}
      },
      "cfg(target_family = \"wasm\")": {
        "dependencies": {}
      }
    }
  },
  {
    "package": {
      "name": "flows-pubsub",
      "version": {
        "workspace": true
      },
      "authors": {
        "workspace": true
      },
      "edition": {
        "workspace": true
      },
      "description": "Building blocks for flow-based publish/subscribe.",
      "readme": true,
      "homepage": {
        "workspace": true
      },
      "repository": {
        "workspace": true
      },
      "license": {
        "workspace": true
      },
      "keywords": {
        "workspace": true
      },
      "categories": {
        "workspace": true
      },
      "publish": {
        "workspace": true
      },
      "metadata": {
        "readme": {
          "title": "Flows.rs: Publish/Subscribe"
        }
      }
    },
    "features": {
      "default": [
        "all",
        "std"
      ],
      "all": [],
      "std": [
        "async-flow/std"
      ],
      "unstable": [],
      "amqp": [],
      "dds": [
        "dep:rustdds"
      ],
      "kafka": [
        "dep:kafka-protocol"
      ],
      "mqtt": [],
      "nats": [
        "dep:async-nats"
      ],
      "nsq": [],
      "postgres": [
        "dep:tokio-postgres"
      ],
      "redis": [
        "dep:redis"
      ],
      "ros1": [],
      "ros2": [],
      "stomp": [
        "dep:iridium-stomp"
      ],
      "valkey": [
        "redis"
      ],
      "zenoh": [
        "dep:zenoh"
      ],
      "zeromq": []
    },
    "dependencies": {
      "async-flow": {
        "workspace": true
      },
      "flows-derive": {
        "workspace": true
      },
      "async-nats": {
        "version": "0.46",
        "default-features": false,
        "optional": true
      },
      "iridium-stomp": {
        "version": "0.3",
        "default-features": false,
        "optional": true
      },
      "kafka-protocol": {
        "version": "0.17",
        "default-features": false,
        "optional": true
      },
      "redis": {
        "version": "0.32",
        "default-features": false,
        "optional": true
      },
      "rustdds": {
        "version": "0.11",
        "default-features": false,
        "optional": true
      },
      "tokio-postgres": {
        "version": "0.7",
        "default-features": false,
        "optional": true
      },
      "zenoh": {
        "version": "1.7",
        "default-features": false,
        "optional": true
      }
    },
    "target": {
      "cfg(not(target_family = \"wasm\"))": {
        "dependencies": {}
      },
      "cfg(target_family = \"wasm\")": {
        "dependencies": {}
      }
    }
  },
  {
    "package": {
      "name": "flows-rand",
      "version": {
        "workspace": true
      },
      "authors": {
        "workspace": true
      },
      "edition": {
        "workspace": true
      },
      "description": "Building blocks for flow-based random number generation.",
      "readme": true,
      "homepage": {
        "workspace": true
      },
      "repository": {
        "workspace": true
      },
      "license": {
        "workspace": true
      },
      "keywords": {
        "workspace": true
      },
      "categories": {
        "workspace": true
      },
      "publish": {
        "workspace": true
      },
      "metadata": {
        "readme": {
          "title": "Flows.rs: Random Number Generation"
        }
      }
    },
    "features": {
      "default": [
        "all",
        "std"
      ],
      "all": [],
      "std": [
        "async-flow/std",
        "getrandom/std"
      ],
      "unstable": []
    },
    "dependencies": {
      "async-flow": {
        "workspace": true
      },
      "flows-derive": {
        "workspace": true
      },
      "getrandom": {
        "version": "0.3",
        "default-features": false
      }
    },
    "target": {
      "cfg(not(target_family = \"wasm\"))": {
        "dependencies": {}
      },
      "cfg(target_family = \"wasm\")": {
        "dependencies": {}
      }
    }
  },
  {
    "package": {
      "name": "flows-text",
      "version": {
        "workspace": true
      },
      "authors": {
        "workspace": true
      },
      "edition": {
        "workspace": true
      },
      "description": "Building blocks for flow-based text processing.",
      "readme": true,
      "homepage": {
        "workspace": true
      },
      "repository": {
        "workspace": true
      },
      "license": {
        "workspace": true
      },
      "keywords": {
        "workspace": true
      },
      "categories": {
        "workspace": true
      },
      "publish": {
        "workspace": true
      },
      "metadata": {
        "readme": {
          "title": "Flows.rs: Text Processing"
        }
      }
    },
    "features": {
      "default": [
        "all",
        "std"
      ],
      "all": [],
      "std": [
        "async-flow/std"
      ],
      "unstable": []
    },
    "dependencies": {
      "async-flow": {
        "workspace": true
      },
      "flows-derive": {
        "workspace": true
      },
      "strsim": {
        "version": "0.11",
        "default-features": false,
        "optional": true
      }
    },
    "target": {
      "cfg(not(target_family = \"wasm\"))": {
        "dependencies": {}
      },
      "cfg(target_family = \"wasm\")": {
        "dependencies": {}
      }
    },
    "dev-dependencies": {
      "tokio": {
        "workspace": true
      }
    }
  },
  {
    "package": {
      "name": "flows-video",
      "version": {
        "workspace": true
      },
      "authors": {
        "workspace": true
      },
      "edition": {
        "workspace": true
      },
      "description": "Building blocks for flow-based video processing.",
      "readme": true,
      "homepage": {
        "workspace": true
      },
      "repository": {
        "workspace": true
      },
      "license": {
        "workspace": true
      },
      "keywords": {
        "workspace": true
      },
      "categories": {
        "workspace": true
      },
      "publish": {
        "workspace": true
      },
      "metadata": {
        "readme": {
          "title": "Flows.rs: Video Processing"
        }
      }
    },
    "features": {
      "default": [
        "all",
        "std"
      ],
      "all": [],
      "std": [
        "async-flow/std"
      ],
      "unstable": [],
      "av1": [
        "dep:rav1e"
      ]
    },
    "dependencies": {
      "async-flow": {
        "workspace": true
      },
      "rav1e": {
        "version": "0.8",
        "default-features": false,
        "optional": true
      }
    },
    "target": {
      "cfg(not(target_family = \"wasm\"))": {
        "dependencies": {}
      },
      "cfg(target_family = \"wasm\")": {
        "dependencies": {}
      }
    }
  }
]
